AUTHORS.rst
CONTRIBUTING.rst
HISTORY.rst
LICENSE
MANIFEST.in
README.rst
setup.cfg
setup.py
badger_batcher/__init__.py
badger_batcher/core.py
badger_batcher/errors.py
badger_batcher/example.py
badger_batcher.egg-info/PKG-INFO
badger_batcher.egg-info/SOURCES.txt
badger_batcher.egg-info/dependency_links.txt
badger_batcher.egg-info/not-zip-safe
badger_batcher.egg-info/top_level.txt
badger_batcher/utils/__init__.py
badger_batcher/utils/iterating.py
docs/Makefile
docs/authors.rst
docs/conf.py
docs/contributing.rst
docs/history.rst
docs/index.rst
docs/installation.rst
docs/make.bat
docs/readme.rst
docs/usage.rst
docs/_build/html/_static/ajax-loader.gif
docs/_build/html/_static/comment-bright.png
docs/_build/html/_static/comment-close.png
docs/_build/html/_static/comment.png
docs/_build/html/_static/down-pressed.png
docs/_build/html/_static/down.png
docs/_build/html/_static/file.png
docs/_build/html/_static/minus.png
docs/_build/html/_static/plus.png
docs/_build/html/_static/up-pressed.png
docs/_build/html/_static/up.png
docs/source/badger_batcher.rst
docs/source/badger_batcher.utils.rst
docs/source/modules.rst
tests/__init__.py
tests/test_badger_batcher.py