Metadata-Version: 1.2
Name: badger-batcher
Version: 0.4.0
Summary: Badger Batcher contains useful utilities for batching a sequence on records
Home-page: https://github.com/tkasu/badger_batcher
Author: Tomi Kasurinen
Author-email: tomi.kasurinen@gmail.com
License: MIT license
Keywords: badger_batcher
Platform: UNKNOWN
Classifier: Development Status :: 2 - Pre-Alpha
Classifier: Intended Audience :: Developers
Classifier: License :: OSI Approved :: MIT License
Classifier: Natural Language :: English
Classifier: Programming Language :: Python :: 3
Classifier: Programming Language :: Python :: 3.8
Classifier: Programming Language :: Python :: 3.9
Requires-Python: >=3.8
